horseAnalysis.py
horseAnalysis-0.0.6.dist-info/METADATA
horseAnalysis-0.0.6.dist-info/WHEEL
horseAnalysis-0.0.6.dist-info/entry_points.txt
horseAnalysis-0.0.6.dist-info/top_level.txt
horseAnalysis-0.0.6.dist-info/RECORD
