Metadata-Version: 2.1
Name: horseAnalysis
Version: 0.0.6
Summary: The system can look up and analyze a horse's history of running famous races.
Home-page: https://github.com/tama2101-s/horseAnalysis
Author: Shota Tamaru
Author-email: s2022022@stu.musashino-u.ac.jp
License: UNKNOWN
Project-URL: Bug Tracker, https://github.com/tama2101-s/horseAnalysis
Platform: UNKNOWN
Classifier: Programming Language :: Python :: 3
Classifier: License :: OSI Approved :: MIT License
Classifier: Operating System :: OS Independent
Requires-Python: >=3.7
